odoo8_addon_web_tree_image-8.0.1.1.0.99.dev13-py2.7-nspkg.pth
odoo8_addon_web_tree_image-8.0.1.1.0.99.dev13.dist-info/DESCRIPTION.rst
odoo8_addon_web_tree_image-8.0.1.1.0.99.dev13.dist-info/METADATA
odoo8_addon_web_tree_image-8.0.1.1.0.99.dev13.dist-info/RECORD
odoo8_addon_web_tree_image-8.0.1.1.0.99.dev13.dist-info/WHEEL
odoo8_addon_web_tree_image-8.0.1.1.0.99.dev13.dist-info/metadata.json
odoo8_addon_web_tree_image-8.0.1.1.0.99.dev13.dist-info/namespace_packages.txt
odoo8_addon_web_tree_image-8.0.1.1.0.99.dev13.dist-info/top_level.txt
odoo_addons/web_tree_image/README.rst
odoo_addons/web_tree_image/__init__.py
odoo_addons/web_tree_image/__openerp__.py
odoo_addons/web_tree_image/i18n/ar.po
odoo_addons/web_tree_image/i18n/de.po
odoo_addons/web_tree_image/i18n/es.po
odoo_addons/web_tree_image/i18n/fi.po
odoo_addons/web_tree_image/i18n/fr.po
odoo_addons/web_tree_image/i18n/hr.po
odoo_addons/web_tree_image/i18n/it.po
odoo_addons/web_tree_image/i18n/pt_BR.po
odoo_addons/web_tree_image/i18n/sl.po
odoo_addons/web_tree_image/i18n/tr.po
odoo_addons/web_tree_image/i18n/web_tree_image.pot
odoo_addons/web_tree_image/static/description/icon.png
odoo_addons/web_tree_image/static/src/js/web_tree_image.js
odoo_addons/web_tree_image/static/src/xml/widget.xml
odoo_addons/web_tree_image/view/assets.xml
